LICENSE
MANIFEST.in
README.md
setup.py
class_tools/__init__.py
class_tools/decorators.py
class_tools/propertyobject.py
class_tools/utils.py
class_tools/version.py
class_tools.egg-info/PKG-INFO
class_tools.egg-info/SOURCES.txt
class_tools.egg-info/dependency_links.txt
class_tools.egg-info/top_level.txt