Metadata-Version: 2.1
Name: class-tools
Version: 0.2.0
Summary: Python class utilities
Home-page: https://gitlab.com/nobodyinperson/python3-class-tools
Author: Yann Büchau
Author-email: nobodyinperson@gmx.de
License: GPLv3
Platform: UNKNOWN
Classifier: License :: OSI Approved :: GNU General Public License v3 (GPLv3)
